[
  {
    "id": "pj2BQP/Wzw02jmPkMNF2+2odh40=",
    "mf": "C3H4O",
    "idCodeHash": "7b0fe64fb05b4270b44579f6c4dd0293",
    "file": "./40_ex5/10_Aufgabe 2/index.json",
    "title": "Aufgabe 2",
    "selected": true
  },
  {
    "id": "39zhIHc/slWJxIeMO9SE8L9Rgvo=",
    "mf": "C8H8O",
    "idCodeHash": "e4617999ccdccfc27ee8da157b5d8bdd",
    "file": "./40_ex5/20_Aufgabe 3/index.json",
    "title": "Aufgabe 3"
  },
  {
    "id": "qDSmGh3YaFbrwsBgu3RCDkhG5Jk=",
    "mf": "C6H10",
    "idCodeHash": "37bda40ad086a34bedb633da0ffa5359",
    "file": "./40_ex5/30_Aufgabe 4/index.json",
    "title": "Aufgabe 4"
  }
]